nbagrapher/__init__.py
nbagrapher/custom_plots.py
nbagrapher/grappher.py
nbagrapher/shot_scraper.py
NBAGrapher-1.1.1.dist-info/LICENSE
NBAGrapher-1.1.1.dist-info/METADATA
NBAGrapher-1.1.1.dist-info/WHEEL
NBAGrapher-1.1.1.dist-info/dependency_links.txt
NBAGrapher-1.1.1.dist-info/top_level.txt
NBAGrapher-1.1.1.dist-info/RECORD
