Metadata-Version: 2.1
Name: NBAGrapher
Version: 1.1.1
Summary: Graphing NBA player and team stats using matplotlib
Home-page: https://github.com/taoprajjwal/NBAGrapher
Author: Prajjwal Bhattarai
Author-email: taoprajjwal@gmail.com
License: MIT
Platform: UNKNOWN
Classifier: License :: OSI Approved :: MIT License
Classifier: Programming Language :: Python :: 3
Classifier: Programming Language :: Python :: 3.7
Requires-Dist: sportsreference
Requires-Dist: matplotlib
Requires-Dist: pandas
